pyclimaterisk/__init__.py
pyclimaterisk/loader.py
pyclimaterisk/data/__init__.py
pyclimaterisk/data/daily.pq
pyclimaterisk/data/events.pq
pyclimaterisk/data/monthly.pq
pyclimaterisk-1.1.1.dist-info/METADATA
pyclimaterisk-1.1.1.dist-info/WHEEL
pyclimaterisk-1.1.1.dist-info/top_level.txt
pyclimaterisk-1.1.1.dist-info/RECORD
