Metadata-Version: 2.1
Name: pyclimaterisk
Version: 1.1.1
Summary: This package provides climate risk data derived from newspapers data
Home-page: https://github.com/muhsinciftci/pyclimaterisk
Author: Muhsin Ciftci
Author-email: farmer.muhsin@gmail.com
License: MIT
Keywords: Climate,Risk,Newspapers,Finance
Platform: UNKNOWN
Requires-Dist: polars (>=1.0.0)
